devx-0.0.0.dist-info/METADATA
devx-0.0.0.dist-info/WHEEL
devx-0.0.0.dist-info/entry_points.txt
devx-0.0.0.dist-info/licenses/LICENSE
devx/__init__.py
devx/__main__.py
devx/cli.py
devx/py.typed
devx-0.0.0.dist-info/RECORD
